eba_file_tracker/__init__.py
eba_file_tracker/client.py
eba_file_tracker/core/__init__.py
eba_file_tracker/core/communication/__init__.py
eba_file_tracker/core/communication/json_transfer.py
eba_file_tracker/core/communication/system.py
eba_file_tracker/core/models/__init__.py
eba_file_tracker/core/models/base.py
eba_file_tracker/core/models/command.py
eba_file_tracker/core/models/result.py
eba_file_tracker/core/models/server.py
eba_file_tracker/core/models/tracker.py
eba_file_tracker/core/tracker.py
eba_file_tracker/response.py
eba_file_tracker/server.py
eba_file_tracker/var/.env
eba_file_tracker-0.1.5.dist-info/METADATA
eba_file_tracker-0.1.5.dist-info/WHEEL
eba_file_tracker-0.1.5.dist-info/entry_points.txt
eba_file_tracker-0.1.5.dist-info/RECORD
